llm_axe/__init__.py
llm_axe/agents.py
llm_axe/core.py
llm_axe/models.py
llm_axe/system_prompts.yaml
llm_axe-1.1.9.dist-info/LICENSE
llm_axe-1.1.9.dist-info/METADATA
llm_axe-1.1.9.dist-info/WHEEL
llm_axe-1.1.9.dist-info/top_level.txt
llm_axe-1.1.9.dist-info/RECORD
