Metadata-Version: 2.1
Name: llm-axe
Version: 1.1.9
Summary: A toolkit for quickly implementing llm powered functionalities.
Author: Emir Sahin
Author-email: emirsah122@gmail.com
License: MIT
Keywords: python,llm axe,llm toolkit,local llm,local llm internet,function caller llm,ollama
Classifier: Development Status :: 3 - Alpha
Classifier: Intended Audience :: Developers
Classifier: Programming Language :: Python :: 3
Classifier: Operating System :: Unix
Classifier: Operating System :: MacOS :: MacOS X
Classifier: Operating System :: Microsoft :: Windows
License-File: LICENSE
